{
  "questions": [
    {
      "topic": "Python Basics",
      "difficulty": 1,
      "question_text": "What is the correct way to create a list in Python?",
      "option_a": "list = []",
      "option_b": "list = {}",
      "option_c": "list = ()",
      "option_d": "list = <>",
      "correct_answer": "A",
      "explanation": "Square brackets [] are used to create lists in Python. Curly braces {} create dictionaries, parentheses () create tuples, and <> is not valid Python syntax."
    },
    {
      "topic": "Python Basics",
      "difficulty": 1,
      "question_text": "Which keyword is used to define a function in Python?",
      "option_a": "function",
      "option_b": "def",
      "option_c": "define",
      "option_d": "func",
      "correct_answer": "B",
      "explanation": "The 'def' keyword is used to define functions in Python. Example: def my_function():"
    },
    {
      "topic": "Python Basics",
      "difficulty": 2,
      "question_text": "Which of the following is a mutable data type in Python?",
      "option_a": "tuple",
      "option_b": "string",
      "option_c": "list",
      "option_d": "integer",
      "correct_answer": "C",
      "explanation": "Lists are mutable, meaning they can be modified after creation. Tuples, strings, and integers are immutable."
    },
    {
      "topic": "Python Basics",
      "difficulty": 2,
      "question_text": "What does the 'len()' function return?",
      "option_a": "The last element",
      "option_b": "The number of elements",
      "option_c": "The first element",
      "option_d": "The type of object",
      "correct_answer": "B",
      "explanation": "len() returns the number of items in an object. For example, len([1,2,3]) returns 3."
    },
    {
      "topic": "Python Basics",
      "difficulty": 3,
      "question_text": "What is the output of: print(type([]))?",
      "option_a": "<class 'list'>",
      "option_b": "<class 'array'>",
      "option_c": "<class 'dict'>",
      "option_d": "<class 'tuple'>",
      "correct_answer": "A",
      "explanation": "type([]) returns <class 'list'> because [] creates an empty list object."
    },
    {
      "topic": "Loops",
      "difficulty": 1,
      "question_text": "Which loop is guaranteed to execute at least once?",
      "option_a": "for loop",
      "option_b": "while loop",
      "option_c": "do-while loop",
      "option_d": "None - Python doesn't guarantee execution",
      "correct_answer": "D",
      "explanation": "Python doesn't have a do-while loop, and both for and while loops check conditions before executing, so they might not run at all."
    },
    {
      "topic": "Loops",
      "difficulty": 2,
      "question_text": "What does 'break' do in a loop?",
      "option_a": "Skips the current iteration",
      "option_b": "Exits the loop completely",
      "option_c": "Restarts the loop",
      "option_d": "Pauses the loop",
      "correct_answer": "B",
      "explanation": "The 'break' statement immediately exits the entire loop. 'continue' skips the current iteration."
    },
    {
      "topic": "Loops",
      "difficulty": 2,
      "question_text": "How do you iterate over a list in Python?",
      "option_a": "foreach item in list:",
      "option_b": "for item in list:",
      "option_c": "loop item in list:",
      "option_d": "iterate item in list:",
      "correct_answer": "B",
      "explanation": "Python uses 'for item in list:' syntax to iterate over lists and other iterables."
    },
    {
      "topic": "Loops",
      "difficulty": 3,
      "question_text": "What is the output of: for i in range(3): print(i)",
      "option_a": "1 2 3",
      "option_b": "0 1 2",
      "option_c": "1 2",
      "option_d": "0 1 2 3",
      "correct_answer": "B",
      "explanation": "range(3) generates numbers from 0 to 2 (3 is not included). Python uses 0-based indexing."
    },
    {
      "topic": "Loops",
      "difficulty": 3,
      "question_text": "What does 'continue' do in a loop?",
      "option_a": "Exits the loop",
      "option_b": "Skips to the next iteration",
      "option_c": "Restarts from beginning",
      "option_d": "Does nothing",
      "correct_answer": "B",
      "explanation": "The 'continue' statement skips the rest of the current iteration and moves to the next one."
    },
    {
      "topic": "Functions",
      "difficulty": 1,
      "question_text": "How do you call a function named 'greet' in Python?",
      "option_a": "call greet()",
      "option_b": "greet()",
      "option_c": "execute greet()",
      "option_d": "run greet()",
      "correct_answer": "B",
      "explanation": "Functions are called by writing their name followed by parentheses: greet()"
    },
    {
      "topic": "Functions",
      "difficulty": 2,
      "question_text": "What keyword is used to return a value from a function?",
      "option_a": "give",
      "option_b": "return",
      "option_c": "output",
      "option_d": "send",
      "correct_answer": "B",
      "explanation": "The 'return' keyword is used to send a value back from a function."
    },
    {
      "topic": "Functions",
      "difficulty": 2,
      "question_text": "What is a parameter in a function?",
      "option_a": "The return value",
      "option_b": "A variable passed to the function",
      "option_c": "The function name",
      "option_d": "A global variable",
      "correct_answer": "B",
      "explanation": "Parameters are variables defined in the function definition that receive values when the function is called."
    },
    {
      "topic": "Functions",
      "difficulty": 3,
      "question_text": "What happens if a function doesn't have a return statement?",
      "option_a": "Returns 0",
      "option_b": "Returns None",
      "option_c": "Causes an error",
      "option_d": "Returns empty string",
      "correct_answer": "B",
      "explanation": "Functions without an explicit return statement automatically return None."
    },
    {
      "topic": "Functions",
      "difficulty": 3,
      "question_text": "What are *args in a function definition?",
      "option_a": "Required arguments",
      "option_b": "Variable number of arguments",
      "option_c": "Keyword arguments",
      "option_d": "Default arguments",
      "correct_answer": "B",
      "explanation": "*args allows a function to accept any number of positional arguments as a tuple."
    },
    {
      "topic": "Data Structures",
      "difficulty": 1,
      "question_text": "Which data structure uses key-value pairs?",
      "option_a": "List",
      "option_b": "Tuple",
      "option_c": "Dictionary",
      "option_d": "Set",
      "correct_answer": "C",
      "explanation": "Dictionaries store data as key-value pairs, allowing fast lookup by key."
    },
    {
      "topic": "Data Structures",
      "difficulty": 2,
      "question_text": "What is the difference between a list and a tuple?",
      "option_a": "Lists are faster",
      "option_b": "Tuples are mutable",
      "option_c": "Lists are mutable, tuples are immutable",
      "option_d": "No difference",
      "correct_answer": "C",
      "explanation": "Lists can be modified after creation (mutable), while tuples cannot be changed (immutable)."
    },
    {
      "topic": "Data Structures",
      "difficulty": 2,
      "question_text": "How do you access a dictionary value with key 'name'?",
      "option_a": "dict.name",
      "option_b": "dict['name']",
      "option_c": "dict(name)",
      "option_d": "dict->name",
      "correct_answer": "B",
      "explanation": "Dictionary values are accessed using square bracket notation: dict['key']"
    },
    {
      "topic": "Data Structures",
      "difficulty": 3,
      "question_text": "What does a set guarantee?",
      "option_a": "Ordered elements",
      "option_b": "Unique elements",
      "option_c": "Mutable elements",
      "option_d": "Indexed access",
      "correct_answer": "B",
      "explanation": "Sets automatically remove duplicates, guaranteeing all elements are unique."
    },
    {
      "topic": "Data Structures",
      "difficulty": 3,
      "question_text": "How do you add an item to a list?",
      "option_a": "list.add(item)",
      "option_b": "list.append(item)",
      "option_c": "list.insert(item)",
      "option_d": "list.push(item)",
      "correct_answer": "B",
      "explanation": "The append() method adds an item to the end of a list."
    },
    {
      "topic": "Conditionals",
      "difficulty": 1,
      "question_text": "Which operator checks if two values are equal?",
      "option_a": "=",
      "option_b": "==",
      "option_c": "===",
      "option_d": "equals()",
      "correct_answer": "B",
      "explanation": "== checks equality, while = is used for assignment. Python doesn't use ===."
    },
    {
      "topic": "Conditionals",
      "difficulty": 2,
      "question_text": "What is the correct syntax for an if-else statement?",
      "option_a": "if x: ... else: ...",
      "option_b": "if (x) { ... } else { ... }",
      "option_c": "if x then ... else ...",
      "option_d": "if x do ... else do ...",
      "correct_answer": "A",
      "explanation": "Python uses 'if condition: ... else: ...' with colons and indentation, no curly braces."
    },
    {
      "topic": "Conditionals",
      "difficulty": 2,
      "question_text": "What does 'elif' stand for?",
      "option_a": "Else if",
      "option_b": "Extra if",
      "option_c": "Either if",
      "option_d": "Evaluate if",
      "correct_answer": "A",
      "explanation": "elif is short for 'else if' and allows checking multiple conditions."
    },
    {
      "topic": "Conditionals",
      "difficulty": 3,
      "question_text": "What is a ternary operator in Python?",
      "option_a": "x ? y : z",
      "option_b": "x if y else z",
      "option_c": "if x then y else z",
      "option_d": "ternary(x, y, z)",
      "correct_answer": "B",
      "explanation": "Python's ternary operator syntax is: value_if_true if condition else value_if_false"
    },
    {
      "topic": "Conditionals",
      "difficulty": 3,
      "question_text": "What does 'not' do in a condition?",
      "option_a": "Inverts the boolean value",
      "option_b": "Checks inequality",
      "option_c": "Negates a number",
      "option_d": "Removes a value",
      "correct_answer": "A",
      "explanation": "'not' inverts boolean values: not True becomes False, not False becomes True."
    },
    {
      "topic": "String Operations",
      "difficulty": 1,
      "question_text": "How do you concatenate two strings in Python?",
      "option_a": "str1 + str2",
      "option_b": "str1.concat(str2)",
      "option_c": "concat(str1, str2)",
      "option_d": "str1 & str2",
      "correct_answer": "A",
      "explanation": "The + operator concatenates strings: 'Hello' + ' World' = 'Hello World'"
    },
    {
      "topic": "String Operations",
      "difficulty": 2,
      "question_text": "What does .upper() do?",
      "option_a": "Capitalizes first letter",
      "option_b": "Converts to uppercase",
      "option_c": "Removes spaces",
      "option_d": "Reverses the string",
      "correct_answer": "B",
      "explanation": ".upper() converts all characters in a string to uppercase."
    },
    {
      "topic": "String Operations",
      "difficulty": 2,
      "question_text": "How do you get the length of a string?",
      "option_a": "string.length",
      "option_b": "len(string)",
      "option_c": "string.size()",
      "option_d": "length(string)",
      "correct_answer": "B",
      "explanation": "len() function returns the number of characters in a string."
    },
    {
      "topic": "String Operations",
      "difficulty": 3,
      "question_text": "What does string slicing [1:4] return?",
      "option_a": "Characters at index 1, 2, 3, 4",
      "option_b": "Characters at index 1, 2, 3",
      "option_c": "Characters at index 0, 1, 2, 3",
      "option_d": "Characters at index 2, 3, 4",
      "correct_answer": "B",
      "explanation": "Slicing [start:end] includes start index but excludes end index. [1:4] gives indices 1, 2, 3."
    },
    {
      "topic": "String Operations",
      "difficulty": 3,
      "question_text": "What is an f-string in Python?",
      "option_a": "A formatted string literal",
      "option_b": "A function string",
      "option_c": "A frozen string",
      "option_d": "A file string",
      "correct_answer": "A",
      "explanation": "f-strings allow embedding expressions inside strings: f'Hello {name}'"
    },
    {
      "topic": "Error Handling",
      "difficulty": 1,
      "question_text": "Which keyword is used to catch exceptions?",
      "option_a": "catch",
      "option_b": "except",
      "option_c": "error",
      "option_d": "handle",
      "correct_answer": "B",
      "explanation": "Python uses try-except blocks for exception handling, not try-catch."
    },
    {
      "topic": "Error Handling",
      "difficulty": 2,
      "question_text": "What does 'finally' do in exception handling?",
      "option_a": "Ends the program",
      "option_b": "Runs regardless of exception",
      "option_c": "Catches all errors",
      "option_d": "Reraises the exception",
      "correct_answer": "B",
      "explanation": "The finally block always executes, whether an exception occurred or not."
    },
    {
      "topic": "Error Handling",
      "difficulty": 2,
      "question_text": "How do you raise an exception manually?",
      "option_a": "throw Exception",
      "option_b": "raise Exception",
      "option_c": "error Exception",
      "option_d": "except Exception",
      "correct_answer": "B",
      "explanation": "Use the 'raise' keyword to manually raise exceptions: raise ValueError('Error message')"
    },
    {
      "topic": "Error Handling",
      "difficulty": 3,
      "question_text": "What is a try-except-else block?",
      "option_a": "Runs else if error occurs",
      "option_b": "Runs else if no error occurs",
      "option_c": "Always runs else",
      "option_d": "Invalid syntax",
      "correct_answer": "B",
      "explanation": "The else block executes only if no exception was raised in the try block."
    },
    {
      "topic": "Error Handling",
      "difficulty": 3,
      "question_text": "What is the base class for all exceptions?",
      "option_a": "Error",
      "option_b": "Exception",
      "option_c": "BaseException",
      "option_d": "StandardError",
      "correct_answer": "C",
      "explanation": "BaseException is the base class for all built-in exceptions in Python."
    },
    {
      "topic": "File Operations",
      "difficulty": 1,
      "question_text": "Which function opens a file in Python?",
      "option_a": "open()",
      "option_b": "file()",
      "option_c": "read()",
      "option_d": "load()",
      "correct_answer": "A",
      "explanation": "The open() function is used to open files: open('filename.txt', 'r')"
    },
    {
      "topic": "File Operations",
      "difficulty": 2,
      "question_text": "What mode opens a file for writing?",
      "option_a": "'r'",
      "option_b": "'w'",
      "option_c": "'a'",
      "option_d": "'x'",
      "correct_answer": "B",
      "explanation": "'w' mode opens a file for writing (creates new or overwrites existing file)."
    },
    {
      "topic": "File Operations",
      "difficulty": 2,
      "question_text": "What does 'with' do when opening files?",
      "option_a": "Reads faster",
      "option_b": "Automatically closes the file",
      "option_c": "Opens multiple files",
      "option_d": "Locks the file",
      "correct_answer": "B",
      "explanation": "The 'with' statement automatically closes files when done, even if errors occur."
    },
    {
      "topic": "File Operations",
      "difficulty": 3,
      "question_text": "What is the difference between 'w' and 'a' modes?",
      "option_a": "'w' overwrites, 'a' appends",
      "option_b": "'a' overwrites, 'w' appends",
      "option_c": "No difference",
      "option_d": "'w' is faster",
      "correct_answer": "A",
      "explanation": "'w' mode overwrites the file, while 'a' mode appends to the end without erasing existing content."
    },
    {
      "topic": "File Operations",
      "difficulty": 3,
      "question_text": "How do you read all lines from a file into a list?",
      "option_a": "file.read()",
      "option_b": "file.readlines()",
      "option_c": "file.getlines()",
      "option_d": "file.lines()",
      "correct_answer": "B",
      "explanation": "readlines() returns a list where each element is a line from the file."
    },
    {
      "topic": "Object-Oriented Programming",
      "difficulty": 2,
      "question_text": "What keyword creates a class in Python?",
      "option_a": "class",
      "option_b": "object",
      "option_c": "def",
      "option_d": "new",
      "correct_answer": "A",
      "explanation": "The 'class' keyword is used to define classes: class MyClass:"
    },
    {
      "topic": "Object-Oriented Programming",
      "difficulty": 2,
      "question_text": "What is __init__ in a Python class?",
      "option_a": "A regular method",
      "option_b": "The constructor",
      "option_c": "A class variable",
      "option_d": "The destructor",
      "correct_answer": "B",
      "explanation": "__init__ is the constructor method called when creating new instances of a class."
    },
    {
      "topic": "Object-Oriented Programming",
      "difficulty": 3,
      "question_text": "What does 'self' represent in a class?",
      "option_a": "The class itself",
      "option_b": "The instance of the class",
      "option_c": "A global variable",
      "option_d": "The parent class",
      "correct_answer": "B",
      "explanation": "'self' refers to the current instance of the class, similar to 'this' in other languages."
    },
    {
      "topic": "Object-Oriented Programming",
      "difficulty": 3,
      "question_text": "What is inheritance in OOP?",
      "option_a": "Copying code",
      "option_b": "A class acquiring properties from another class",
      "option_c": "Hiding data",
      "option_d": "Creating multiple objects",
      "correct_answer": "B",
      "explanation": "Inheritance allows a class to inherit attributes and methods from a parent class."
    },
    {
      "topic": "Object-Oriented Programming",
      "difficulty": 4,
      "question_text": "What is polymorphism?",
      "option_a": "Having multiple constructors",
      "option_b": "Methods with the same name behaving differently",
      "option_c": "Creating many objects",
      "option_d": "Using multiple inheritance",
      "correct_answer": "B",
      "explanation": "Polymorphism allows methods in different classes to have the same name but different implementations."
    },
    {
      "topic": "List Comprehensions",
      "difficulty": 2,
      "question_text": "What is list comprehension?",
      "option_a": "Understanding lists",
      "option_b": "A concise way to create lists",
      "option_c": "Compressing lists",
      "option_d": "Sorting lists",
      "correct_answer": "B",
      "explanation": "List comprehension provides a compact syntax for creating lists: [x*2 for x in range(5)]"
    },
    {
      "topic": "List Comprehensions",
      "difficulty": 3,
      "question_text": "What does [x for x in range(5)] create?",
      "option_a": "[1, 2, 3, 4, 5]",
      "option_b": "[0, 1, 2, 3, 4]",
      "option_c": "[0, 1, 2, 3, 4, 5]",
      "option_d": "[5, 4, 3, 2, 1]",
      "correct_answer": "B",
      "explanation": "This creates a list [0, 1, 2, 3, 4] as range(5) generates 0 to 4."
    },
    {
      "topic": "List Comprehensions",
      "difficulty": 3,
      "question_text": "How do you add a condition to list comprehension?",
      "option_a": "[x for x in list if condition]",
      "option_b": "[x if condition for x in list]",
      "option_c": "[x for x in list where condition]",
      "option_d": "[x for x in list when condition]",
      "correct_answer": "A",
      "explanation": "Conditions are added at the end: [x for x in range(10) if x % 2 == 0]"
    }
  ]
}
